cfanalytics/__init__.py
cfanalytics/core/__init__.py
cfanalytics/core/affiliatelist.py
cfanalytics/core/cfopendata.py
cfanalytics/core/cfplot.py
cfanalytics/core/clean.py
cfanalytics/core/utils.py
cfanalytics/tests/__init__.py
cfanalytics/tests/test_affiliatelist.py
cfanalytics/tests/test_cfopendata.py
cfanalytics/tests/test_cfplot.py
cfanalytics/tests/test_clean.py
cfanalytics/tests/test_utils.py
cfanalytics-0.1.10.dist-info/DESCRIPTION.rst
cfanalytics-0.1.10.dist-info/METADATA
cfanalytics-0.1.10.dist-info/RECORD
cfanalytics-0.1.10.dist-info/WHEEL
cfanalytics-0.1.10.dist-info/metadata.json
cfanalytics-0.1.10.dist-info/top_level.txt
