Metadata-Version: 2.0
Name: cfanalytics
Version: 0.1.10
Summary: Downloading, analyzing and visualizing CrossFit data
Home-page: https://github.com/raybellwaves/cfanalytics
Author: Ray Bell
Author-email: rbell1987@gmail.com
License: BSD 3-Clause License
Platform: UNKNOWN
Requires-Python: >=3.6
Requires-Dist: requests
Requires-Dist: aiohttp
Requires-Dist: pandas
Requires-Dist: numpy
Requires-Dist: xarray
